fatcat_openapi_client/__init__.py
fatcat_openapi_client/__version__.py
fatcat_openapi_client/api_client.py
fatcat_openapi_client/configuration.py
fatcat_openapi_client/exceptions.py
fatcat_openapi_client/rest.py
fatcat_openapi_client/api/__init__.py
fatcat_openapi_client/api/default_api.py
fatcat_openapi_client/models/__init__.py
fatcat_openapi_client/models/auth_oidc.py
fatcat_openapi_client/models/auth_oidc_result.py
fatcat_openapi_client/models/auth_token_result.py
fatcat_openapi_client/models/changelog_entry.py
fatcat_openapi_client/models/container_auto_batch.py
fatcat_openapi_client/models/container_entity.py
fatcat_openapi_client/models/creator_auto_batch.py
fatcat_openapi_client/models/creator_entity.py
fatcat_openapi_client/models/editgroup.py
fatcat_openapi_client/models/editgroup_annotation.py
fatcat_openapi_client/models/editgroup_edits.py
fatcat_openapi_client/models/editor.py
fatcat_openapi_client/models/entity_edit.py
fatcat_openapi_client/models/entity_history_entry.py
fatcat_openapi_client/models/error_response.py
fatcat_openapi_client/models/file_auto_batch.py
fatcat_openapi_client/models/file_entity.py
fatcat_openapi_client/models/file_url.py
fatcat_openapi_client/models/fileset_auto_batch.py
fatcat_openapi_client/models/fileset_entity.py
fatcat_openapi_client/models/fileset_file.py
fatcat_openapi_client/models/fileset_url.py
fatcat_openapi_client/models/release_abstract.py
fatcat_openapi_client/models/release_auto_batch.py
fatcat_openapi_client/models/release_contrib.py
fatcat_openapi_client/models/release_entity.py
fatcat_openapi_client/models/release_ext_ids.py
fatcat_openapi_client/models/release_ref.py
fatcat_openapi_client/models/success.py
fatcat_openapi_client/models/webcapture_auto_batch.py
fatcat_openapi_client/models/webcapture_cdx_line.py
fatcat_openapi_client/models/webcapture_entity.py
fatcat_openapi_client/models/webcapture_url.py
fatcat_openapi_client/models/work_auto_batch.py
fatcat_openapi_client/models/work_entity.py
fatcat_openapi_client-0.5.0.dist-info/METADATA
fatcat_openapi_client-0.5.0.dist-info/WHEEL
fatcat_openapi_client-0.5.0.dist-info/top_level.txt
fatcat_openapi_client-0.5.0.dist-info/RECORD
