Metadata-Version: 2.1
Name: fatcat-openapi-client
Version: 0.5.0
Summary: API client library for fatcat.wiki (a bibliographic catalog)
Home-page: https://github.com/internetarchive/fatcat
Author: Bryan Newbold
Author-email: bnewbold@archive.org
License: CC-0
Keywords: fatcat,OpenAPI
Platform: UNKNOWN
Classifier: Development Status :: 3 - Alpha
Classifier: Intended Audience :: Developers
Classifier: Programming Language :: Python
Classifier: Programming Language :: Python :: 3
Classifier: Programming Language :: Python :: 3.5
Requires-Python: >=3.5.0
Requires-Dist: certifi
Requires-Dist: python-dateutil
Requires-Dist: six (>=1.10)
Requires-Dist: urllib3 (>=1.15)
